odoo/addons/stock_barcodes_gs1_secondary_unit/README.rst
odoo/addons/stock_barcodes_gs1_secondary_unit/__init__.py
odoo/addons/stock_barcodes_gs1_secondary_unit/__manifest__.py
odoo/addons/stock_barcodes_gs1_secondary_unit/i18n/es.po
odoo/addons/stock_barcodes_gs1_secondary_unit/i18n/stock_barcodes_gs1_secondary_unit.pot
odoo/addons/stock_barcodes_gs1_secondary_unit/models/__init__.py
odoo/addons/stock_barcodes_gs1_secondary_unit/models/product_second_unit.py
odoo/addons/stock_barcodes_gs1_secondary_unit/models/stock_barcodes_read_log.py
odoo/addons/stock_barcodes_gs1_secondary_unit/models/stock_move_line.py
odoo/addons/stock_barcodes_gs1_secondary_unit/readme/CONTRIBUTORS.rst
odoo/addons/stock_barcodes_gs1_secondary_unit/readme/DESCRIPTION.rst
odoo/addons/stock_barcodes_gs1_secondary_unit/readme/USAGE.rst
odoo/addons/stock_barcodes_gs1_secondary_unit/static/description/icon.png
odoo/addons/stock_barcodes_gs1_secondary_unit/static/description/index.html
odoo/addons/stock_barcodes_gs1_secondary_unit/tests/__init__.py
odoo/addons/stock_barcodes_gs1_secondary_unit/tests/test_stock_barcodes_gs1_secondary_unit.py
odoo/addons/stock_barcodes_gs1_secondary_unit/views/product_views.xml
odoo/addons/stock_barcodes_gs1_secondary_unit/wizard/__init__.py
odoo/addons/stock_barcodes_gs1_secondary_unit/wizard/stock_barcodes_read.py
odoo/addons/stock_barcodes_gs1_secondary_unit/wizard/stock_barcodes_read_picking.py
odoo/addons/stock_barcodes_gs1_secondary_unit/wizard/stock_barcodes_read_picking_views.xml
odoo/addons/stock_barcodes_gs1_secondary_unit/wizard/stock_barcodes_read_todo.py
odoo/addons/stock_barcodes_gs1_secondary_unit/wizard/stock_barcodes_read_todo_view.xml
odoo_addon_stock_barcodes_gs1_secondary_unit-15.0.1.1.0.dist-info/METADATA
odoo_addon_stock_barcodes_gs1_secondary_unit-15.0.1.1.0.dist-info/WHEEL
odoo_addon_stock_barcodes_gs1_secondary_unit-15.0.1.1.0.dist-info/top_level.txt
odoo_addon_stock_barcodes_gs1_secondary_unit-15.0.1.1.0.dist-info/RECORD
