Metadata-Version: 2.1
Name: odoo-addon-stock_barcodes_gs1_secondary_unit
Version: 15.0.1.1.0
Summary: It provides read package from GS1 barcode stored into secondary unit data.
Home-page: https://github.com/OCA/stock-logistics-barcode
Author: Tecnativa, Odoo Community Association (OCA)
Author-email: support@odoo-community.org
License: AGPL-3
Classifier: Programming Language :: Python
Classifier: Framework :: Odoo
Classifier: Framework :: Odoo :: 15.0
Classifier: License :: OSI Approved :: GNU Affero General Public License v3
Requires-Python: >=3.8
Requires-Dist: odoo-addon-stock-barcodes-gs1<15.1dev,>=15.0dev
Requires-Dist: odoo-addon-stock-secondary-unit<15.1dev,>=15.0dev
Requires-Dist: odoo<15.1dev,>=15.0a
